<?xml version="1.0"?>
<servers>
    <server>
        <server-name>Local</server-name>
        <server-url>jdbc:mysql://localhost:3306/</server-url>
        <server-default>false</server-default>
        <database>
            <db-name>pupone_pm</db-name>
            <db-username></db-username>
            <db-password></db-password>
            <db-default></db-default>
        </database>
    </server>
    <server>
        <server-name>pupone</server-name>
        <server-url>jdbc:mysql://serve658.arvixevps.com:3306/</server-url>
        <server-default>false</server-default>
        <database>
            <db-name>pupone_PM</db-name>
            <db-username></db-username>
            <db-password></db-password>
            <db-default></db-default>
        </database>
    </server>
</servers>